{
  "versionCode": 11,
  "versionName": "X5",
  "isMaintenance": false,
  "changelog": "🚀 Release Notes: vX5 (Version Code 11)\n\n✨ UI/UX Update\n- Redesign MainMenuScreen dengan animasi press (bouncy scale effect).\n- Animated border glow pada menu cards saat ditekan.\n- Radial gradient pada icon backgrounds untuk visual lebih dalam.\n- Layout scrollable untuk support layar kecil.\n- Status bar padding yang lebih rapi.\n- Optimasi spacing, tipografi, dan interaksi sentuhan.\n\n🐛 Perbaikan\n- Peningkatan responsivitas dan smoothness animasi UI.\n\nCatatan: rilis ini fokus pada pengalaman visual dan kenyamanan penggunaan.",
  "downloadUrl": "https://github.com/sonzaiekkusu/SonzaiEkkusu/releases/download/X5/SonzaixBox-X5.apk"
}
